mcp_deploy/__init__.py
mcp_deploy/__main__.py
mcp_deploy/mcp_handlers.py
mcp_deploy/models.py
mcp_deploy/server.py
cloudstudio_mcp_server-1.0.10.dist-info/METADATA
cloudstudio_mcp_server-1.0.10.dist-info/WHEEL
cloudstudio_mcp_server-1.0.10.dist-info/entry_points.txt
cloudstudio_mcp_server-1.0.10.dist-info/RECORD
