Metadata-Version: 2.4
Name: cloudstudio-mcp-server
Version: 1.0.10
Summary: Cloud Studio MCP Server
Author-email: hongxuwu <hongxuwu@tencent.com>, chrisclye <chrisclye@tencent.com>
Keywords: cloudstudio,deploy,mcp
Requires-Python: >=3.10
Requires-Dist: fastapi
Requires-Dist: fastmcp>=2.11.3
Requires-Dist: httpx
Requires-Dist: mcp
Requires-Dist: pydantic
Requires-Dist: requests
Requires-Dist: uvicorn
